lambdata-witt/__init__.py
lambdata-witt/helper_functions.py
lambdata_witt/__init__.py
lambdata_witt/helper_functions.py
lambdata_witt-0.0.2.dist-info/LICENSE
lambdata_witt-0.0.2.dist-info/METADATA
lambdata_witt-0.0.2.dist-info/WHEEL
lambdata_witt-0.0.2.dist-info/top_level.txt
lambdata_witt-0.0.2.dist-info/RECORD
